streamchat_bot/__init__.py
streamchat_bot/streamchat_bot.py
streamchat_bot-0.1.0.dist-info/METADATA
streamchat_bot-0.1.0.dist-info/WHEEL
streamchat_bot-0.1.0.dist-info/top_level.txt
streamchat_bot-0.1.0.dist-info/RECORD
